{
  "schemaVersion": 1,
  "id": "2026-04-28-ai-lead-follow-up-setup-for-service-businesses",
  "platform": "landing-page",
  "language": "en",
  "date": "2026-04-28",
  "dayOfWeek": "tuesday",
  "published": {
    "text": "### Hero\nHeading: AI Lead Follow-Up Setup for Service Businesses\nBody: Most lead follow-up automation fails not because the tool is wrong but because the setup was incomplete. The system goes live without clear response rules, without tested CRM connections, without a plan for what happens when a lead replies at 11 PM or submits through a channel nobody mapped, and without the sequencing logic that makes multi-touch follow-up useful instead of annoying. The difference between a lead follow-up system that actually converts and one that sends messages into the void is almost always in setup scope — what was configured before launch and how carefully the edge cases were tested. This page covers what a service business should expect from a proper lead follow-up setup, when professional implementation help is worth the spend, and when a lighter workflow handles the real need.\nSub: Below: what setup actually involves, the response logic that matters most, what should be configured before launch, and how to tell whether you need full setup help or a simpler path.\n\n### Core sections\n- What lead follow-up setup actually covers (response logic, sequencing, CRM integration, edge-case testing)\n- What should be configured before launch (speed-to-lead rules, stop conditions, CRM mapping, alert routing)\n- When setup help is worth paying for — and when it is not (fit/not-fit evaluation)\n- Common setup mistakes that break lead follow-up workflows (unmapped sources, skipped stop conditions, CRM-before-channels)\n\n### Proof\n- E-commerce CRM case study as adjacent proof for setup quality\n- Contact form follow-up page as narrower first-build scope\n- Lead follow-up cost page for budgeting after setup scope is clear\n\n### FAQ\nSubhead: Practical answers for service business owners evaluating lead follow-up implementation\nTopics: what setup involves, how long it takes, self-service versus professional help, most common setup mistake, how this differs from the parent page.\n\n### Final CTA\nHeading: Want to get lead follow-up set up properly?\nBody: Book a 30-minute call. We will look at your lead sources, response gaps, CRM setup, and follow-up needs, then scope the narrowest build that handles your real speed-to-lead problem.",
    "formatting": [
      "bold:###"
    ]
  },
  "draft": null,
  "engagement": null,
  "edits": [
    {
      "type": "tone_shift",
      "description": "Shipped as a cross-industry child page under the lead follow-up cluster, filling the setup-scope gap between the parent (what lead follow-up is) and the cost/ROI children (what it costs and whether it pays back)."
    },
    {
      "type": "tone_shift",
      "description": "Stays distinct from the parent by focusing on implementation rather than workflow value, from the cost child by focusing on what gets configured rather than what it costs, and from the ROI child by focusing on setup quality rather than payback math."
    },
    {
      "type": "tone_shift",
      "description": "Proof framing stays honest: e-commerce CRM case study as adjacent proof, contact form follow-up as narrower first scope, lead follow-up cost page for budgeting after setup clarity."
    },
    {
      "type": "tone_shift",
      "description": "Tone stays practical and non-hype: fit/not-fit evaluation, explicit setup-mistake framing, and clear separation from the parent and cost/ROI siblings."
    }
  ],
  "analysis": {
    "analyzedAt": "2026-04-30T06:27:04.916Z",
    "structure": {
      "paragraphCount": 5,
      "sentencesPerParagraph": [
        5,
        1,
        1,
        1,
        3
      ],
      "avgSentenceLength": 31.2,
      "sentenceLengthRange": [
        5,
        61
      ],
      "totalWords": 343
    },
    "opener": {
      "type": "general",
      "text": "### Hero\nHeading: AI Lead Follow-Up Setup for Service Businesses\nBody: Most lead follow-up automation fails not because the tool is wrong but because the setup was incomplete.",
      "wordCount": 27,
      "pattern": "standard-opener"
    },
    "closer": {
      "type": "question",
      "text": "### Final CTA\nHeading: Want to get lead follow-up set up properly?\nBody: Book a 30-minute call. We will look at your lead sources, response gaps, CRM setup, and follow-up needs, then scope the narrowest build that handles your real speed-to-lead problem.",
      "pattern": "question"
    },
    "template": {
      "roles": [
        "opener",
        "context",
        "context",
        "product-pitch",
        "closer"
      ],
      "template": "opener | context | context | product-pitch | closer"
    },
    "punctuation": {
      "periods": 8,
      "commas": 24,
      "emDashes": 2,
      "enDashes": 0,
      "hyphens": 7,
      "ellipsis": 0,
      "exclamation": 0,
      "question": 1,
      "colon": 8,
      "commasPerSentence": 2.67
    },
    "vocabulary": {
      "distinctWords": 180,
      "totalWords": 343,
      "topWords": [
        [
          "setup",
          14
        ],
        [
          "follow-up",
          12
        ],
        [
          "lead",
          11
        ],
        [
          "what",
          8
        ],
        [
          "-",
          7
        ],
        [
          "that",
          6
        ],
        [
          "crm",
          5
        ],
        [
          "when",
          5
        ],
        [
          "without",
          4
        ],
        [
          "response",
          4
        ],
        [
          "scope",
          4
        ],
        [
          "how",
          4
        ],
        [
          "page",
          4
        ],
        [
          "help",
          4
        ],
        [
          "service",
          3
        ]
      ],
      "casualMarkers": [],
      "formalWords": [],
      "buzzwords": [],
      "casualMarkerRate": 0
    },
    "editSignals": {
      "totalEdits": 4,
      "cuts": 0,
      "additions": 0,
      "wordSwaps": 0,
      "rephrases": 0,
      "reorders": 0,
      "toneShifts": 4,
      "patterns": []
    }
  }
}
